windows_tools.office-0.1.4-py3.8-nspkg.pth
windows_tools/office/__init__.py
windows_tools.office-0.1.4.dist-info/LICENSE
windows_tools.office-0.1.4.dist-info/METADATA
windows_tools.office-0.1.4.dist-info/WHEEL
windows_tools.office-0.1.4.dist-info/namespace_packages.txt
windows_tools.office-0.1.4.dist-info/top_level.txt
windows_tools.office-0.1.4.dist-info/RECORD
